orangetool/__init__.py
orangetool/__main__.py
orangetool/orangetool_display.py
orangetool/orangetool_ip.py
orangetool/orangetool_params.py
orangetool/orangetool_ram.py
orangetool/orangetool_storage.py
orangetool/orangetool_system.py
orangetool/orangetool_test.py
orangetool/orangetool_utils.py
orangetool-0.50.dist-info/AUTHORS.md
orangetool-0.50.dist-info/LICENSE
orangetool-0.50.dist-info/METADATA
orangetool-0.50.dist-info/WHEEL
orangetool-0.50.dist-info/top_level.txt
orangetool-0.50.dist-info/RECORD
