Metadata-Version: 2.1
Name: orangetool
Version: 0.50
Summary: Some useful script for Orangepi/Raspberrypi boards
Home-page: https://github.com/Moduland/Orangetool
Author: Moduland Co
Author-email: info@orangetool.ir
License: MIT
Download-URL: https://github.com/Moduland/Orangetool/tarball/v0.50
Keywords: orangepi raspberrypi embedded-systems python
Platform: UNKNOWN
Classifier: Development Status :: 4 - Beta
Classifier: Intended Audience :: Developers
Classifier: Natural Language :: English
Classifier: License :: OSI Approved :: MIT License
Classifier: Operating System :: Unix
Classifier: Intended Audience :: Developers
Classifier: Programming Language :: Python :: 3.5
Classifier: Programming Language :: Python :: 3.6
Classifier: Programming Language :: Python :: 3.7
Classifier: Programming Language :: Python :: 3.8
Classifier: Programming Language :: Python :: 3.9
Classifier: Topic :: Scientific/Engineering
Requires-Dist: psutil (>=5.2.1)
Requires-Dist: requests (>=2.14.0)
Requires-Dist: art (>=0.9)
